odoo8_addon_account_chart_report-8.0.1.0.0-py2.7-nspkg.pth
odoo8_addon_account_chart_report-8.0.1.0.0.dist-info/top_level.txt
odoo8_addon_account_chart_report-8.0.1.0.0.dist-info/WHEEL
odoo8_addon_account_chart_report-8.0.1.0.0.dist-info/RECORD
odoo8_addon_account_chart_report-8.0.1.0.0.dist-info/metadata.json
odoo8_addon_account_chart_report-8.0.1.0.0.dist-info/DESCRIPTION.rst
odoo8_addon_account_chart_report-8.0.1.0.0.dist-info/METADATA
odoo8_addon_account_chart_report-8.0.1.0.0.dist-info/namespace_packages.txt
odoo_addons/account_chart_report/__openerp__.py
odoo_addons/account_chart_report/account_report.xml
odoo_addons/account_chart_report/__init__.py
odoo_addons/account_chart_report/README.rst
odoo_addons/account_chart_report/report/chart_of_accounts.py
odoo_addons/account_chart_report/report/__init__.py
odoo_addons/account_chart_report/report/chart_of_accounts.rml
odoo_addons/account_chart_report/i18n/account_chart_report.pot
odoo_addons/account_chart_report/i18n/fr.po
odoo_addons/account_chart_report/wizard/account_report_chart_of_account.py
odoo_addons/account_chart_report/wizard/__init__.py
odoo_addons/account_chart_report/wizard/account_report_chart_of_account.xml
